nnUNet_package/__init__.py
nnUNet_package/main.py
nnUNet_package/models.json
nnUNet_package/predict.py
nnunet_package-0.2.2.dist-info/METADATA
nnunet_package-0.2.2.dist-info/WHEEL
nnunet_package-0.2.2.dist-info/entry_points.txt
nnunet_package-0.2.2.dist-info/top_level.txt
nnunet_package-0.2.2.dist-info/RECORD
