Metadata-Version: 2.4
Name: nnUNet_package
Version: 0.2.2
Summary: Package pour l'utilisation de nnUNet avec 3D Slicer
Author-email: Florian Davaux <florian.davaux@cpe.fr>
License: MIT
Project-URL: Homepage, https://github.com/FlorianDAVAUX/nnUNet_package
Requires-Python: >=3.9
Requires-Dist: SimpleITK>=2.2.1
Requires-Dist: numpy==1.26.4
Requires-Dist: blosc2==2.5.1
Requires-Dist: nnunetv2
